snorkel_lite-0.0.30.data/purelib/snorkel/__init__.py
snorkel_lite-0.0.30.data/purelib/snorkel/admin.py
snorkel_lite-0.0.30.data/purelib/snorkel/auth.py
snorkel_lite-0.0.30.data/purelib/snorkel/backend.py
snorkel_lite-0.0.30.data/purelib/snorkel/cli.py
snorkel_lite-0.0.30.data/purelib/snorkel/fastjson.py
snorkel_lite-0.0.30.data/purelib/snorkel/grafana.py
snorkel_lite-0.0.30.data/purelib/snorkel/main.py
snorkel_lite-0.0.30.data/purelib/snorkel/models.py
snorkel_lite-0.0.30.data/purelib/snorkel/oauth.py
snorkel_lite-0.0.30.data/purelib/snorkel/pages.py
snorkel_lite-0.0.30.data/purelib/snorkel/presenter.py
snorkel_lite-0.0.30.data/purelib/snorkel/query_spec.py
snorkel_lite-0.0.30.data/purelib/snorkel/rbac.py
snorkel_lite-0.0.30.data/purelib/snorkel/results.py
snorkel_lite-0.0.30.data/purelib/snorkel/util.py
snorkel_lite-0.0.30.data/purelib/snorkel/version.py
snorkel_lite-0.0.30.data/purelib/snorkel/web.py
snorkel_lite-0.0.30.data/purelib/snorkel/backend/__init__.py
snorkel_lite-0.0.30.data/purelib/snorkel/backend/backend.py
snorkel_lite-0.0.30.data/purelib/snorkel/backend/msybil.py
snorkel_lite-0.0.30.data/purelib/snorkel/backend/msybil_ingest.py
snorkel_lite-0.0.30.data/purelib/snorkel/backend/sybil.py
snorkel_lite-0.0.30.data/purelib/snorkel/backend/bin/sybil
snorkel_lite-0.0.30.data/purelib/snorkel/components/__init__.py
snorkel_lite-0.0.30.data/purelib/snorkel/components/components.py
snorkel_lite-0.0.30.data/purelib/snorkel/components/query_sidebar.py
snorkel_lite-0.0.30.data/purelib/snorkel/components/sf_components.py
snorkel_lite-0.0.30.data/purelib/snorkel/components/tour.py
snorkel_lite-0.0.30.data/purelib/snorkel/components/user_button.py
snorkel_lite-0.0.30.data/purelib/snorkel/components/TourCarousel/TourCarousel.html
snorkel_lite-0.0.30.data/purelib/snorkel/components/TourCarousel/TourCarousel.js
snorkel_lite-0.0.30.data/purelib/snorkel/components/pages/DatasetsPage/DatasetsPage.js
snorkel_lite-0.0.30.dist-info/LICENSE.md
snorkel_lite-0.0.30.dist-info/METADATA
snorkel_lite-0.0.30.dist-info/WHEEL
snorkel_lite-0.0.30.dist-info/entry_points.txt
snorkel_lite-0.0.30.dist-info/top_level.txt
snorkel_lite-0.0.30.dist-info/RECORD
