Metadata-Version: 2.1
Name: snorkel-lite
Version: 0.0.30
Summary: a data exploration UI
Home-page: UNKNOWN
Author: okay
Author-email: okayzed+slite@gmail.com
License: UNKNOWN
Platform: UNKNOWN
Requires-Dist: addict
Requires-Dist: bcrypt
Requires-Dist: email-validator
Requires-Dist: flask
Requires-Dist: flask-admin
Requires-Dist: flask-dance
Requires-Dist: flask-peewee
Requires-Dist: flask-security
Requires-Dist: parsedatetime
Requires-Dist: peewee (==3.9.2)
Requires-Dist: python-geoip
Requires-Dist: python-geoip-geolite2
Requires-Dist: preparable
Requires-Dist: pudgy (>=0.1.6)
Requires-Dist: werkzeug (==0.16.1)
